modello.py
modello-0.1.0.post1.dist-info/METADATA
modello-0.1.0.post1.dist-info/WHEEL
modello-0.1.0.post1.dist-info/top_level.txt
modello-0.1.0.post1.dist-info/RECORD
