Metadata-Version: 2.1
Name: modello
Version: 0.1.0.post1
Summary: sympy expressions in models
Home-page: https://github.com/Code0x58/modello/
Author: Oliver Bristow
Author-email: github+pypi@oliverbristow.co.uk
License: MIT
Keywords: symbolic modeling
Platform: UNKNOWN
Classifier: Development Status :: 4 - Beta
Classifier: Intended Audience :: Developers
Classifier: Intended Audience :: Science/Research
Classifier: License :: OSI Approved :: MIT License
Classifier: Operating System :: OS Independent
Classifier: Programming Language :: Python :: 3
Requires-Python: >=3.3
Requires-Dist: sympy
Provides-Extra: test
Requires-Dist: flake8-docstrings ; extra == 'test'
Requires-Dist: flake8-isort ; extra == 'test'
Requires-Dist: pytest-cov (>=2.6.1) ; extra == 'test'
Requires-Dist: pytest-flake8 ; extra == 'test'
Requires-Dist: pytest-mypy ; extra == 'test'
Requires-Dist: pytest (>=4.1) ; extra == 'test'
